kampvie_example/__init__.py
kampvie_example/example.py
kampvie_example-0.1.dist-info/WHEEL
kampvie_example-0.1.dist-info/METADATA
kampvie_example-0.1.dist-info/RECORD
